MANIFEST.in
README.md
requirements.txt
setup.py
keras_gcn/__init__.py
keras_gcn/layers.py
keras_gcn.egg-info/PKG-INFO
keras_gcn.egg-info/SOURCES.txt
keras_gcn.egg-info/dependency_links.txt
keras_gcn.egg-info/top_level.txt
tests/__init__.py
tests/test_graph_conv.py
tests/test_graph_pool.py