Metadata-Version: 2.1
Name: keras-gcn
Version: 0.15.0
Summary: Graph convolutional layers
Home-page: https://github.com/CyberZHG/keras-gcn
Author: CyberZHG
Author-email: CyberZHG@users.noreply.github.com
License: MIT
Platform: UNKNOWN
Classifier: Programming Language :: Python :: 2.7
Classifier: Programming Language :: Python :: 3.6
Classifier: License :: OSI Approved :: MIT License
Classifier: Operating System :: OS Independent
